keypress/__init__.py
keypress/key.py
keypress-0.1.7.dist-info/LICENSE
keypress-0.1.7.dist-info/METADATA
keypress-0.1.7.dist-info/WHEEL
keypress-0.1.7.dist-info/RECORD
