Metadata-Version: 2.1
Name: keypress
Version: 0.1.7
Summary: Cross-Platform Key Handling Module: Effortlessly Detect and Describe Keyboard Events
Author: hyperoot
Author-email: rajesh@hyperoot.dev
Requires-Python: >=3.12,<4.0
Classifier: Programming Language :: Python :: 3
Classifier: Programming Language :: Python :: 3.12
